{
  "timestamp": "2025-12-07T14:50:37.092995",
  "stage": "03_before_render_slot5",
  "data": {
    "slot_number": 5,
    "subject": "Math",
    "render_type": "multi_slot",
    "metadata_slot_number": 5,
    "metadata_subject": "Math",
    "hyperlink_count": 66,
    "all_hyperlinks_have_slot": true,
    "all_hyperlinks_have_subject": true,
    "hyperlink_slot_distribution": {
      "5": 66
    },
    "sample_hyperlinks": [
      {
        "text": "3.3.8 Teacher Guide",
        "source_slot": 5,
        "source_subject": "Math"
      },
      {
        "text": "3.3.9 Teacher Guide",
        "source_slot": 5,
        "source_subject": "Math"
      },
      {
        "text": "3.3.10 Teacher Guide",
        "source_slot": 5,
        "source_subject": "Math"
      },
      {
        "text": "3.3.11 Teacher Guide",
        "source_slot": 5,
        "source_subject": "Math"
      },
      {
        "text": "SUBTRACT ",
        "source_slot": 5,
        "source_subject": "Math"
      },
      {
        "text": "STRATEGICALLY",
        "source_slot": 5,
        "source_subject": "Math"
      },
      {
        "text": "3.3.12 Teacher Guide",
        "source_slot": 5,
        "source_subject": "Math"
      },
      {
        "text": "Five in a Row: Mult. & Division ",
        "source_slot": 5,
        "source_subject": "Math"
      },
      {
        "text": "Stage 2",
        "source_slot": 5,
        "source_subject": "Math"
      },
      {
        "text": "How Close?",
        "source_slot": 5,
        "source_subject": "Math"
      },
      {
        "text": "Stage 4",
        "source_slot": 5,
        "source_subject": "Math"
      },
      {
        "text": "Number Puzzles",
        "source_slot": 5,
        "source_subject": "Math"
      },
      {
        "text": "Stage 5",
        "source_slot": 5,
        "source_subject": "Math"
      },
      {
        "text": "3.3 Section B: Practice Problems",
        "source_slot": 5,
        "source_subject": "Math"
      },
      {
        "text": "Number Puzzles",
        "source_slot": 5,
        "source_subject": "Math"
      }
    ]
  }
}